oustro/__init__.py
oustro/add.py
oustro/chain.py
oustro-0.2.1.dist-info/METADATA
oustro-0.2.1.dist-info/WHEEL
oustro-0.2.1.dist-info/top_level.txt
oustro-0.2.1.dist-info/RECORD
