Metadata-Version: 2.1
Name: oustro
Version: 0.2.1
Summary: Oustro Package
Home-page: UNKNOWN
Author: Jacob Thomas
Author-email: jacobt1206@gmail.com
License: UNKNOWN
Keywords: python,oustro,blockchain,Oustrochain
Platform: UNKNOWN
Classifier: Development Status :: 3 - Alpha
Classifier: Intended Audience :: Developers
Classifier: Programming Language :: Python :: 3
Classifier: Operating System :: MacOS :: MacOS X
Classifier: Operating System :: Microsoft :: Windows
Requires-Dist: requests
